LICENSE.txt
MANIFEST.in
README.rst
VERSION
nlist.py
setup.py
nlist.egg-info/PKG-INFO
nlist.egg-info/SOURCES.txt
nlist.egg-info/dependency_links.txt
nlist.egg-info/top_level.txt