Metadata-Version: 1.1
Name: nlist
Version: 0.1
Summary: A lightweight multidimensional list in Python
Home-page: https://github.com/swarmer/nlist
Author: Anton Barkovsky
Author-email: anton@swarmer.me
License: MIT
Keywords: array list container multidimensional
Platform: UNKNOWN
Classifier: Development Status :: 4 - Beta
Classifier: Intended Audience :: Developers
Classifier: Topic :: Software Development :: Libraries :: Python Modules
Classifier: License :: OSI Approved :: MIT License
Classifier: Programming Language :: Python :: 3
Classifier: Programming Language :: Python :: 3.4
